verilog/r_design.v
module co (
    input [7:0] rooms,
    input clk,
    output reg [3:0] count,
    output reg [3:0] countdown0,
    output reg [3:0] countdown1,
    output reg [3:0] countdown2,
    output reg [3:0] countdown3,
    output reg [3:0] countdown4,
    output reg [3:0] countdown5,
    output reg [3:0] countdown6,
    output reg [3:0] countdown7,
    output reg [7:0] lightson,
    input [1:0]x,
    input [1:0]y,
    output reg[2:0] sum
);
    integer i;
    reg [3:0] countdown_array [7:0];  // internal array
    function [2:0] add;
    	input[1:0] x;
		input[1:0] y;
		begin
			add = x + y;
		end
	endfunction
    initial begin
        countdown_array[0] = 4'd0;
        countdown_array[1] = 4'd0;
        countdown_array[2] = 4'd0;
        countdown_array[3] = 4'd0;
        countdown_array[4] = 4'd0;
        countdown_array[5] = 4'd0;
        countdown_array[6] = 4'd0;
        countdown_array[7] = 4'd0;
        for (i = 0;i < 8;i = i+1) begin
        	lightson[i] = 0;
        end
    end

    always @(posedge clk) begin
        count = 4'd0;

        for (i = 0; i < 8; i = i + 1) begin
            if (rooms[i] == 1'b1) begin
                count = count + 1;
                lightson[i] = 1;
            end
        end
		
		for (i = 0;i < 8;i = i+1) begin
        	if (count<6 && rooms[i]==1'b1)begin
        		lightson[i] = 1;
        		countdown_array[i] = 4'd10;
        	end
        	else if(count>5 && rooms[i]==1'b1)begin
        		lightson[i] = 1;
        		countdown_array[i] = 4'd5;
        	end
        	else if((count>5 ||count<6)&&(rooms[i]==1'b0)&&countdown_array[i]>4'd0)begin
        		countdown_array[i] = countdown_array[i] -1;
        	end
        	
        	if(countdown_array[i]==4'd0)begin
        		lightson[i] = 0;
        	end
        end
		sum = add(x,y);
        // assign internal array to individual outputs
        countdown0 = countdown_array[0];
        countdown1 = countdown_array[1];
        countdown2 = countdown_array[2];
        countdown3 = countdown_array[3];
        countdown4 = countdown_array[4];
        countdown5 = countdown_array[5];
        countdown6 = countdown_array[6];
        countdown7 = countdown_array[7];
    end
endmodule

verilog/r_tb.v
module room;
    reg clk;
    reg [7:0] rooms;
    wire [3:0] count;
    wire [3:0] countdown0, countdown1, countdown2, countdown3;
    wire [3:0] countdown4, countdown5, countdown6, countdown7;
    wire [7:0] lightson;
    reg [1:0] x;
    reg [1:0] y;
    wire [2:0] sum;

    co uut(
        .clk(clk),
        .rooms(rooms),
        .count(count),
        .countdown0(countdown0),
        .countdown1(countdown1),
        .countdown2(countdown2),
        .countdown3(countdown3),
        .countdown4(countdown4),
        .countdown5(countdown5),
        .countdown6(countdown6),
        .countdown7(countdown7),
        .lightson(lightson),
        .x(x),
        .y(y),
        .sum(sum)
    );
	initial begin
		$dumpfile("room.vcd");
		$dumpvars(0,room);
	end
    initial begin
        clk = 0;
        forever #5 clk = ~clk;
    end

    initial begin
        $monitor("Time=%0t | Rooms=%b | Count=%d | CD: [%d %d %d %d %d %d %d %d],Lightson:%b, sum:%d", 
            $time, rooms, count,
            countdown0, countdown1, countdown2, countdown3,
            countdown4, countdown5, countdown6, countdown7,lightson,sum);
		x = 2'b00;
		y = 2'b10;
        rooms = 8'b00000000; #10;
        rooms = 8'b00010010; #10;
        rooms = 8'b11111111; #10;
        rooms = 8'b00000000; #10;
        #100;
        rooms = 8'b00000001;#100;
        $finish;
    end
endmodule

verilog/room.vcd
$date
	Mon Apr 21 13:14:07 2025
$end
$version
	Icarus Verilog
$end
$timescale
	1s
$end
$scope module room $end
$var wire 3 ! sum [2:0] $end
$var wire 8 " lightson [7:0] $end
$var wire 4 # countdown7 [3:0] $end
$var wire 4 $ countdown6 [3:0] $end
$var wire 4 % countdown5 [3:0] $end
$var wire 4 & countdown4 [3:0] $end
$var wire 4 ' countdown3 [3:0] $end
$var wire 4 ( countdown2 [3:0] $end
$var wire 4 ) countdown1 [3:0] $end
$var wire 4 * countdown0 [3:0] $end
$var wire 4 + count [3:0] $end
$var reg 1 , clk $end
$var reg 8 - rooms [7:0] $end
$var reg 2 . x [1:0] $end
$var reg 2 / y [1:0] $end
$scope module uut $end
$var wire 1 , clk $end
$var wire 8 0 rooms [7:0] $end
$var wire 2 1 x [1:0] $end
$var wire 2 2 y [1:0] $end
$var reg 4 3 count [3:0] $end
$var reg 4 4 countdown0 [3:0] $end
$var reg 4 5 countdown1 [3:0] $end
$var reg 4 6 countdown2 [3:0] $end
$var reg 4 7 countdown3 [3:0] $end
$var reg 4 8 countdown4 [3:0] $end
$var reg 4 9 countdown5 [3:0] $end
$var reg 4 : countdown6 [3:0] $end
$var reg 4 ; countdown7 [3:0] $end
$var reg 8 < lightson [7:0] $end
$var reg 3 = sum [2:0] $end
$var integer 32 > i [31:0] $end
$scope function add $end
$var reg 3 ? add [2:0] $end
$var reg 2 @ x [1:0] $end
$var reg 2 A y [1:0] $end
$upscope $end
$upscope $end
$upscope $end
$enddefinitions $end
#0
$dumpvars
bx A
bx @
bx ?
b1000 >
bx =
b0 <
bx ;
bx :
bx 9
bx 8
bx 7
bx 6
bx 5
bx 4
bx 3
b10 2
b0 1
b0 0
b10 /
b0 .
b0 -
0,
bx +
bx *
bx )
bx (
bx '
bx &
bx %
bx $
bx #
b0 "
bx !
$end
#5
b0 #
b0 ;
b0 $
b0 :
b0 %
b0 9
b0 &
b0 8
b0 '
b0 7
b0 (
b0 6
b0 )
b0 5
b0 *
b0 4
b10 !
b10 =
b10 ?
b0 @
b10 A
b1000 >
b0 +
b0 3
1,
#10
0,
b10010 -
b10010 0
#15
b1010 &
b1010 8
b1010 )
b1010 5
b10010 "
b10010 <
b10 +
b10 3
b1000 >
1,
#20
0,
b11111111 -
b11111111 0
#25
b101 #
b101 ;
b101 $
b101 :
b101 %
b101 9
b101 &
b101 8
b101 '
b101 7
b101 (
b101 6
b101 )
b101 5
b101 *
b101 4
b11111111 "
b11111111 <
b1000 >
b1000 +
b1000 3
1,
#30
0,
b0 -
b0 0
#35
b100 #
b100 ;
b100 $
b100 :
b100 %
b100 9
b100 &
b100 8
b100 '
b100 7
b100 (
b100 6
b100 )
b100 5
b100 *
b100 4
b1000 >
b0 +
b0 3
1,
#40
0,
#45
b11 #
b11 ;
b11 $
b11 :
b11 %
b11 9
b11 &
b11 8
b11 '
b11 7
b11 (
b11 6
b11 )
b11 5
b11 *
b11 4
b1000 >
1,
#50
0,
#55
b10 #
b10 ;
b10 $
b10 :
b10 %
b10 9
b10 &
b10 8
b10 '
b10 7
b10 (
b10 6
b10 )
b10 5
b10 *
b10 4
b1000 >
1,
#60
0,
#65
b1 #
b1 ;
b1 $
b1 :
b1 %
b1 9
b1 &
b1 8
b1 '
b1 7
b1 (
b1 6
b1 )
b1 5
b1 *
b1 4
b1000 >
1,
#70
0,
#75
b0 #
b0 ;
b0 $
b0 :
b0 %
b0 9
b0 &
b0 8
b0 '
b0 7
b0 (
b0 6
b0 )
b0 5
b0 *
b0 4
b0 "
b0 <
b1000 >
1,
#80
0,
#85
b1000 >
1,
#90
0,
#95
b1000 >
1,
#100
0,
#105
b1000 >
1,
#110
0,
#115
b1000 >
1,
#120
0,
#125
b1000 >
1,
#130
0,
#135
b1000 >
1,
#140
0,
b1 -
b1 0
#145
b1010 *
b1010 4
b1 "
b1 <
b1 +
b1 3
b1000 >
1,
#150
0,
#155
b1000 >
b1 +
b1 3
1,
#160
0,
#165
b1000 >
b1 +
b1 3
1,
#170
0,
#175
b1000 >
b1 +
b1 3
1,
#180
0,
#185
b1000 >
b1 +
b1 3
1,
#190
0,
#195
b1000 >
b1 +
b1 3
1,
#200
0,
#205
b1000 >
b1 +
b1 3
1,
#210
0,
#215
b1000 >
b1 +
b1 3
1,
#220
0,
#225
b1000 >
b1 +
b1 3
1,
#230
0,
#235
b1000 >
b1 +
b1 3
1,
